setup.py
SBKodiak/KodiakControl.py
SBKodiak/KodiakGlobals.py
SBKodiak/KodiakMDNsLocate.py
SBKodiak/RestFunctions.py
SBKodiak/__init__.py
SBKodiak/kodiak_endpoints.py
SBKodiak/kodiak_session_management.py
SBKodiak/sb_db.py
SBKodiak.egg-info/PKG-INFO
SBKodiak.egg-info/SOURCES.txt
SBKodiak.egg-info/dependency_links.txt
SBKodiak.egg-info/not-zip-safe
SBKodiak.egg-info/requires.txt
SBKodiak.egg-info/top_level.txt
SBKodiak/docs/__init__.py
SBKodiak/docs/conf.py
SBKodiak/tests/__init__.py
SBKodiak/tests/frigged_responses.py
SBKodiak/tests/kodiak_lifecycle.py
SBKodiak/tests/kodiak_locate_tests.py
SBKodiak/tests/kodiak_lock_tests.py
SBKodiak/tests/kodiak_login_tests.py
SBKodiak/tests/pytest_examples.py
SBKodiak/tests/test_app.py