Metadata-Version: 2.1
Name: SBKodiak
Version: 1.1.9
Summary: SanBlaze Python control of Kodiak Modules
Home-page: https://www.sanblaze.com/
Author: Matt Holsey
Author-email: mholsey@sanblaze.com
License: SanBlaze Technology ltd
Platform: UNKNOWN
